CHANGES.txt
README.txt
setup.py
experimental/__init__.py
experimental.portalfactoryfix.egg-info/PKG-INFO
experimental.portalfactoryfix.egg-info/SOURCES.txt
experimental.portalfactoryfix.egg-info/dependency_links.txt
experimental.portalfactoryfix.egg-info/namespace_packages.txt
experimental.portalfactoryfix.egg-info/not-zip-safe
experimental.portalfactoryfix.egg-info/requires.txt
experimental.portalfactoryfix.egg-info/top_level.txt
experimental/portalfactoryfix/__init__.py
experimental/portalfactoryfix/apply.py
experimental/portalfactoryfix/configure.zcml
experimental/portalfactoryfix/interfaces.py
experimental/portalfactoryfix/patch.py