Metadata-Version: 1.0
Name: experimental.portalfactoryfix
Version: 0.4.2
Summary: Plone fix for portal factory not to cause zodb writes
Home-page: http://dev.plone.org/collective/browser/experimental.portalfactoryfix
Author: Kapil Thangavelu
Author-email: kapil.foss@gmail.com
License: GPL
Platform: UNKNOWN
Classifier: Framework :: Plone
Classifier: Programming Language :: Python
